pahomqttmock/__init__.py
pahomqttmock/mock.py
paho_mqtt_mock-1.1.1.dist-info/LICENSE
paho_mqtt_mock-1.1.1.dist-info/METADATA
paho_mqtt_mock-1.1.1.dist-info/WHEEL
paho_mqtt_mock-1.1.1.dist-info/top_level.txt
paho_mqtt_mock-1.1.1.dist-info/RECORD
