Metadata-Version: 2.1
Name: paho-mqtt-mock
Version: 1.1.1
Summary: Simple mock library wrapping paho-mqtt for unit testing
Author-email: Marco Melletti <melletti.marco@gmail.com>
Classifier: Programming Language :: Python :: 3
Classifier: Operating System :: OS Independent
Requires-Python: >=3.7
License-File: LICENSE
Requires-Dist: paho-mqtt
